LICENSE
MANIFEST.in
README.md
requirements.txt
setup.py
PythonProject_KC.egg-info/PKG-INFO
PythonProject_KC.egg-info/SOURCES.txt
PythonProject_KC.egg-info/dependency_links.txt
PythonProject_KC.egg-info/entry_points.txt
PythonProject_KC.egg-info/requires.txt
PythonProject_KC.egg-info/top_level.txt
bin/pythonproject
docs/index.md
docs/about/authors.md
docs/about/changelog.md
docs/about/license.md
docs/about/references.md
pythonproject/__init__.py
pythonproject/__main__.py
pythonproject/settings.py