Metadata-Version: 2.1
Name: PythonProject-KC
Version: 0.1.5
Summary: Python project template
Home-page: https://github.com/kchennen/PythonProject
Author: kchennen
Author-email: author@mail.com
License: MIT
Download-URL: https://github.com/kchennen/PythonProject
Keywords: Python,cookiecutter,unittest,project templates,example,documentation,tutorial,setup.py,package
Platform: UNKNOWN
Classifier: Development Status :: 2 - Pre-Alpha
Classifier: Environment :: X11 Applications
Classifier: Framework :: Flake8
Classifier: Framework :: Flask
Classifier: Framework :: Jupyter
Classifier: Framework :: Matplotlib
Classifier: Framework :: Pytest
Classifier: Framework :: Setuptools Plugin
Classifier: Framework :: tox
Classifier: Intended Audience :: Developers
Classifier: Intended Audience :: Education
Classifier: Intended Audience :: Science/Research
Classifier: Intended Audience :: End Users/Desktop
Classifier: License :: OSI Approved :: MIT License
Classifier: Natural Language :: English
Classifier: Operating System :: POSIX :: Linux
Classifier: Programming Language :: Python :: 3.6
Classifier: Programming Language :: Python :: 3.7
Classifier: Programming Language :: Python :: 3.8
Classifier: Programming Language :: Python :: 3.9
Classifier: Topic :: Scientific/Engineering :: Bio-Informatics
Classifier: Topic :: Scientific/Engineering :: Artificial Intelligence
